conu/__init__.py
conu/exceptions.py
conu/version.py
conu/apidefs/__init__.py
conu/apidefs/backend.py
conu/apidefs/container.py
conu/apidefs/filesystem.py
conu/apidefs/image.py
conu/apidefs/metadata.py
conu/backend/__init__.py
conu/backend/buildah/__init__.py
conu/backend/buildah/backend.py
conu/backend/buildah/constants.py
conu/backend/buildah/container.py
conu/backend/buildah/image.py
conu/backend/buildah/utils.py
conu/backend/docker/__init__.py
conu/backend/docker/backend.py
conu/backend/docker/client.py
conu/backend/docker/constants.py
conu/backend/docker/container.py
conu/backend/docker/container_parameters.py
conu/backend/docker/image.py
conu/backend/docker/skopeo.py
conu/backend/docker/utils.py
conu/backend/k8s/__init__.py
conu/backend/k8s/backend.py
conu/backend/k8s/client.py
conu/backend/k8s/deployment.py
conu/backend/k8s/pod.py
conu/backend/k8s/service.py
conu/backend/k8s/utils.py
conu/backend/nspawn/__init__.py
conu/backend/nspawn/backend.py
conu/backend/nspawn/constants.py
conu/backend/nspawn/container.py
conu/backend/nspawn/image.py
conu/backend/origin/__init__.py
conu/backend/origin/backend.py
conu/backend/origin/constants.py
conu/backend/origin/registry.py
conu/backend/podman/__init__.py
conu/backend/podman/backend.py
conu/backend/podman/constants.py
conu/backend/podman/container.py
conu/backend/podman/image.py
conu/backend/podman/utils.py
conu/fixtures/__init__.py
conu/helpers/__init__.py
conu/helpers/docker_backend.py
conu/utils/__init__.py
conu/utils/filesystem.py
conu/utils/http_client.py
conu/utils/probes.py
conu/utils/rpms.py
conu-1.0.0.dist-info/LICENSE
conu-1.0.0.dist-info/METADATA
conu-1.0.0.dist-info/WHEEL
conu-1.0.0.dist-info/top_level.txt
conu-1.0.0.dist-info/RECORD
