Metadata-Version: 2.1
Name: conu
Version: 1.0.0
Summary: Container testing library
Home-page: https://github.com/user-cont/conu
Author: Red Hat
Author-email: user-cont-team@redhat.com
License: MIT
Keywords: containers,testing
Platform: UNKNOWN
Classifier: Development Status :: 4 - Beta
Classifier: Environment :: Console
Classifier: Intended Audience :: Developers
Classifier: License :: OSI Approved :: MIT License
Classifier: Operating System :: POSIX :: Linux
Classifier: Programming Language :: Python
Classifier: Topic :: Software Development
Requires-Dist: requests
Requires-Dist: six
Requires-Dist: docker
Requires-Dist: kubernetes (==8.0.0)
Requires-Dist: pytest
